clandestino_interfaces/__init__.py
clandestino_interfaces/abstract.py
clandestino_interfaces/enum.py
clandestino_interfaces/interface.py
clandestino_interfaces-0.1.1.dist-info/LICENSE
clandestino_interfaces-0.1.1.dist-info/METADATA
clandestino_interfaces-0.1.1.dist-info/WHEEL
clandestino_interfaces-0.1.1.dist-info/RECORD
