Metadata-Version: 2.1
Name: clandestino-interfaces
Version: 0.1.1
Summary: Clandestino base interfaces
Author: XimitGaia
Author-email: im.ximit@gmail.com
Requires-Python: >=3.11,<4.0
Classifier: Programming Language :: Python :: 3
Classifier: Programming Language :: Python :: 3.11
